canvaz/__init__.py
canvaz/core.py
canvaz/log.py
canvaz-1.0.1.dist-info/METADATA
canvaz-1.0.1.dist-info/WHEEL
canvaz-1.0.1.dist-info/top_level.txt
canvaz-1.0.1.dist-info/RECORD
