Metadata-Version: 2.4
Name: canvaz
Version: 1.0.1
Summary: Add your description here
Requires-Python: >=3.10
Requires-Dist: pytest>=8.4.1
Requires-Dist: python-box>=7.3.2
Requires-Dist: toml>=0.10.2
